gdrive_tools/__init__.py
gdrive_tools/gdrive_tools.py
gdrive_tools/google_accesslevel.py
gdrive_tools/google_auth.py
gdrive_tools/google_filetypes.py
gdrive_tools/google_grant_type.py
gdrive_tools-1.4.0.dist-info/LICENSE
gdrive_tools-1.4.0.dist-info/METADATA
gdrive_tools-1.4.0.dist-info/WHEEL
gdrive_tools-1.4.0.dist-info/top_level.txt
gdrive_tools-1.4.0.dist-info/RECORD
