Metadata-Version: 2.1
Name: gdrive-tools
Version: 1.4.0
Summary: A collection of usefull tools to interact with the google drive/google docs api.
Home-page: https://github.com/5minds/GDrive-Tools
Author: Robin Palkovits
Author-email: robin.palkovits@5minds.de
License: mit
Platform: UNKNOWN
Classifier: Programming Language :: Python :: 3
Classifier: License :: OSI Approved :: MIT License
Classifier: Operating System :: OS Independent
Requires-Python: >=3.6
Requires-Dist: google-api-python-client
Requires-Dist: google-auth-httplib2
Requires-Dist: google-auth-oauthlib
